{
	"01C0" : 
	{
		"device_list" : 
		[
			"23D755971B30",
			"87DE55971B30"
		],
		"group_name" : "门厅分组",
		"location" : 
		{
			"room_name" : "门厅",
			"room_no" : "1"
		},
		"sourceSite" : "EDGE_DC_97_58_43_2C_BB:ble_light"
	},
	"02C0" : 
	{
		"device_list" : 
		[
			"A0DE55971B30",
			"04D555971B30"
		],
		"group_name" : "客厅电视周边",
		"location" : 
		{
			"room_name" : "客厅",
			"room_no" : "1"
		},
		"sourceSite" : "EDGE_DC_97_58_43_2C_BB:ble_light"
	},
	"03C0" : 
	{
		"device_list" : 
		[
			"69DB55971B30",
			"F0E555971B30"
		],
		"group_name" : "客厅背景光",
		"location" : 
		{
			"room_name" : "客厅",
			"room_no" : "1"
		},
		"sourceSite" : "EDGE_DC_97_58_43_2C_BB:ble_light"
	},
	"04C0" : 
	{
		"device_list" : 
		[
			"4BD455971B30"
		],
		"group_name" : "厨房6",
		"location" : 
		{
			"room_name" : "厨房",
			"room_no" : "1"
		},
		"sourceSite" : "EDGE_DC_97_58_43_2C_BB:ble_light"
	},
	"05C0" : 
	{
		"device_list" : 
		[
			"86DE55971B30"
		],
		"group_name" : "厨房7",
		"location" : 
		{
			"room_name" : "厨房",
			"room_no" : "1"
		},
		"sourceSite" : "EDGE_DC_97_58_43_2C_BB:ble_light"
	},
	"06C0" : 
	{
		"device_list" : 
		[
			"221546971B30"
		],
		"group_name" : "厨房8",
		"location" : 
		{
			"room_name" : "厨房",
			"room_no" : "1"
		},
		"sourceSite" : "EDGE_DC_97_58_43_2C_BB:ble_light"
	}
}
